<?xml version="1.0" encoding="UTF-8"?>
<objects serializationModel="Studio.01.10.00">
    <object class="AudioFile" id="{37b6a9cc-e802-47fc-a464-1350069b15c2}">
        <property name="assetPath">
            <value>Ambition - Military - Intimate Conversation - Prologue - LOOP - Rev3 - HORNS.wav</value>
        </property>
        <property name="isStreaming">
            <value>true</value>
        </property>
        <property name="frequencyInKHz">
            <value>48</value>
        </property>
        <property name="channelCount">
            <value>2</value>
        </property>
        <property name="length">
            <value>93.125</value>
        </property>
        <relationship name="masterAssetFolder">
            <destination>{bb8f1aa8-d728-4184-93e7-77c0e236d1b8}</destination>
        </relationship>
    </object>
</objects>
