<?xml version="1.0" encoding="UTF-8"?>
<objects serializationModel="Studio.01.10.00">
    <object class="AudioFile" id="{dbe16d7e-295a-4449-a7a3-b0620f0d7566}">
        <property name="assetPath">
            <value>Female_bark_charmed_02.wav</value>
        </property>
        <property name="frequencyInKHz">
            <value>44.0999985</value>
        </property>
        <property name="channelCount">
            <value>1</value>
        </property>
        <property name="length">
            <value>1.1081632653061224</value>
        </property>
        <relationship name="masterAssetFolder">
            <destination>{bb8f1aa8-d728-4184-93e7-77c0e236d1b8}</destination>
        </relationship>
    </object>
</objects>
